AUTHORS.rst
CONTRIBUTING.rst
HISTORY.rst
LICENSE
MANIFEST.in
README.rst
setup.cfg
setup.py
versioneer.py
docs/Makefile
docs/authors.rst
docs/conf.py
docs/contributing.rst
docs/history.rst
docs/index.rst
docs/installation.rst
docs/make.bat
docs/readme.rst
docs/usage.rst
photo_tools/__init__.py
photo_tools/_version.py
photo_tools/utils.py
photo_tools.egg-info/PKG-INFO
photo_tools.egg-info/SOURCES.txt
photo_tools.egg-info/dependency_links.txt
photo_tools.egg-info/not-zip-safe
photo_tools.egg-info/top_level.txt
photo_tools/data/exif_column_map.json
tests/__init__.py
tests/test_photo_tools.py